Metadata-Version: 2.1
Name: fengye1966-distributions
Version: 0.1
Summary: Gaussian distributions by fengye1966
Author: fengye1966
Author-email: fengye1966@163.com
